password/display.v
module display (
    input [2:0] state,
    output reg [6:0] HEX4, HEX3, HEX2, HEX1, HEX0
);
    always @(*) begin
        case(state)
            3'b110: begin  // COMPLETE
                HEX4 = 7'b1111111;  // Off
                HEX3 = 7'b0100001;  // d
                HEX2 = 7'b1000000;  // o
                HEX1 = 7'b1001000;  // n
                HEX0 = 7'b0000110;  // e
            end
            3'b101: begin  // ERROR
                HEX4 = 7'b0000110;  // E
                HEX3 = 7'b0101111;  // R
                HEX2 = 7'b0101111;  // R
                HEX1 = 7'b0100011;  // O
                HEX0 = 7'b0101111;  // R
            end
            default: begin  // Others
                HEX4 = 7'b1111111;  // Off
                HEX3 = 7'b1111111;  // Off
                HEX2 = 7'b1111111;  // Off
                HEX1 = 7'b1111111;  // Off
                HEX0 = 7'b1111111;  // Off
            end
        endcase
    end
endmodule

password/password.v
module fsm_controller (
    input clk,
    input rst_n,
    input [9:0] sw_rise,
    output reg [2:0] state
);
    localparam IDLE     = 3'b000,
               SW2      = 3'b001,
               SW0      = 3'b010,
               SW1      = 3'b011,
               SW6      = 3'b100,
               ERROR    = 3'b101,
               COMPLETE = 3'b110;

    always @(posedge clk or negedge rst_n) begin
        if (!rst_n) begin
            state <= IDLE;
        end
        else begin
            case(state)
                IDLE: begin
                    if (sw_rise[2]) begin
                        state <= SW2;
                    end
                    else if (|sw_rise) begin
                        state <= ERROR;
                    end
                    else begin
                        state <= IDLE;
                    end
                end
                
                SW2: begin
                    if (sw_rise[0]) begin
                        state <= SW0;
                    end
                    else if (|sw_rise) begin
                        state <= ERROR;
                    end
                    else begin
                        state <= SW2;
                    end
                end
                
                SW0: begin
                    if (sw_rise[1]) begin
                        state <= SW1;
                    end
                    else if (|sw_rise) begin
                        state <= ERROR;
                    end
                    else begin
                        state <= SW0;
                    end
                end
                
                SW1: begin
                    if (sw_rise[6]) begin
                        state <= COMPLETE;
                    end
                    else if (|sw_rise) begin
                        state <= ERROR;
                    end
                    else begin
                        state <= SW1;
                    end
                end
                
                ERROR: begin
                    state <= ERROR;
                end
                
                COMPLETE: begin
                    state <= COMPLETE;
                end
                
                default: begin
                    state <= IDLE;
                end
            endcase
        end
    end
endmodule

password/edge.v
module edge_detector (
    input clk,
    input rst_n,
    input [9:0] sw_clean,
    output reg [9:0] sw_rise
);
    reg [9:0] sw_prev;
    
    always @(posedge clk or negedge rst_n) begin
        if (!rst_n) begin
            sw_prev <= 0;
            sw_rise <= 0;
        end else begin
            sw_prev <= sw_clean;
            sw_rise <= sw_clean & ~sw_prev;
        end
    end
endmodule

password/debouncer.v
module debounce (
    input clk,
    input rst_n,
    input [9:0] sw,
    output reg [9:0] sw_clean
);
    reg [19:0] counter;
    
    always @(posedge clk or negedge rst_n) begin
        if (!rst_n) begin
            counter <= 0;
            sw_clean <= 0;
        end else begin
            if (counter == 20'd1_000_000) begin
                sw_clean <= sw;
                counter <= 0;
            end else begin
                counter <= counter + 1;
            end
        end
    end
endmodule

password/top_psw.v
module top_psw (
    input [9:0] sw,
    input clk,
    input rst_n,
    output [6:0] HEX4, HEX3, HEX2, HEX1, HEX0
);
    
    wire [9:0] sw_clean;
    wire [9:0] sw_rise;
    wire [2:0] current_state;

   
    debounce debounce_inst(
        .clk(clk),
        .rst_n(rst_n),
        .sw(sw),
        .sw_clean(sw_clean)
    );

    edge_detector edge_inst(
        .clk(clk),
        .rst_n(rst_n),
        .sw_clean(sw_clean),
        .sw_rise(sw_rise)
    );

    fsm_controller fsm_inst(
        .clk(clk),
        .rst_n(rst_n),
        .sw_rise(sw_rise),
        .state(current_state)
    );

    display display_inst(
        .state(current_state),
        .HEX4(HEX4),
        .HEX3(HEX3),
        .HEX2(HEX2),
        .HEX1(HEX1),
        .HEX0(HEX0)
    );
endmodule

password/tb_top_psw.v
`timescale 1ns/1ps


module debouncer(
    input clk,
    input rst_n,
    input [9:0] sw,
    output [9:0] sw_clean
);
    assign sw_clean = sw;
endmodule


module tb_top_psw;
    reg clk;
    reg rst_n;
    reg [9:0] sw;
    wire [6:0] HEX4, HEX3, HEX2, HEX1, HEX0;

    top_psw uut (
        .sw(sw),
        .clk(clk),
        .rst_n(rst_n),
        .HEX4(HEX4),
        .HEX3(HEX3),
        .HEX2(HEX2),
        .HEX1(HEX1),
        .HEX0(HEX0)
    );

   
    wire [2:0] current_state;
    assign current_state = uut.fsm_inst.state;


    initial begin
        clk = 0;
        forever #5 clk = ~clk;
    end

   
    initial begin
        $dumpfile("top_psw.vcd");
        $dumpvars(0, tb_top_psw);
    end


    initial begin
        // Initialize inputs
        rst_n = 0;
        sw = 10'b0;
        @(posedge clk);  
        @(posedge clk);
        rst_n = 1;      
        @(posedge clk);
        
      
        sw = 10'b00000100;
        @(posedge clk);
        sw = 10'b0;
        @(posedge clk);
        
        
        sw = 10'b00000001;
        @(posedge clk);
        sw = 10'b0;
        @(posedge clk);
        
       
        sw = 10'b00000010;
        @(posedge clk);
        sw = 10'b0;
        @(posedge clk);
        
        
        sw = 10'b01000000;
        @(posedge clk);
        sw = 10'b0;
        @(posedge clk);
        
      
        repeat (3) @(posedge clk);
        $finish;
    end

  
    initial begin
        $monitor("Time=%0t ns | sw=%b | current_state=%b | HEX4=%b HEX3=%b HEX2=%b HEX1=%b HEX0=%b",
                 $time, sw, current_state, HEX4, HEX3, HEX2, HEX1, HEX0);
    end
endmodule

password/simulation/questa/top_psw.vcd
$date
	Fri Mar 14 16:40:29 2025
$end
$version
	Questa Intel Starter FPGA Edition Version 2023.3
$end
$timescale
	1ps
$end

$scope module tb_top_psw $end
$var reg 1 ! clk $end
$var reg 1 " rst_n $end
$var reg 10 # sw [9:0] $end
$var wire 1 $ HEX4 [6] $end
$var wire 1 % HEX4 [5] $end
$var wire 1 & HEX4 [4] $end
$var wire 1 ' HEX4 [3] $end
$var wire 1 ( HEX4 [2] $end
$var wire 1 ) HEX4 [1] $end
$var wire 1 * HEX4 [0] $end
$var wire 1 + HEX3 [6] $end
$var wire 1 , HEX3 [5] $end
$var wire 1 - HEX3 [4] $end
$var wire 1 . HEX3 [3] $end
$var wire 1 / HEX3 [2] $end
$var wire 1 0 HEX3 [1] $end
$var wire 1 1 HEX3 [0] $end
$var wire 1 2 HEX2 [6] $end
$var wire 1 3 HEX2 [5] $end
$var wire 1 4 HEX2 [4] $end
$var wire 1 5 HEX2 [3] $end
$var wire 1 6 HEX2 [2] $end
$var wire 1 7 HEX2 [1] $end
$var wire 1 8 HEX2 [0] $end
$var wire 1 9 HEX1 [6] $end
$var wire 1 : HEX1 [5] $end
$var wire 1 ; HEX1 [4] $end
$var wire 1 < HEX1 [3] $end
$var wire 1 = HEX1 [2] $end
$var wire 1 > HEX1 [1] $end
$var wire 1 ? HEX1 [0] $end
$var wire 1 @ HEX0 [6] $end
$var wire 1 A HEX0 [5] $end
$var wire 1 B HEX0 [4] $end
$var wire 1 C HEX0 [3] $end
$var wire 1 D HEX0 [2] $end
$var wire 1 E HEX0 [1] $end
$var wire 1 F HEX0 [0] $end
$var wire 1 G current_state [2] $end
$var wire 1 H current_state [1] $end
$var wire 1 I current_state [0] $end

$scope module uut $end
$var wire 1 J sw [9] $end
$var wire 1 K sw [8] $end
$var wire 1 L sw [7] $end
$var wire 1 M sw [6] $end
$var wire 1 N sw [5] $end
$var wire 1 O sw [4] $end
$var wire 1 P sw [3] $end
$var wire 1 Q sw [2] $end
$var wire 1 R sw [1] $end
$var wire 1 S sw [0] $end
$var wire 1 T clk $end
$var wire 1 U rst_n $end
$var wire 1 $ HEX4 [6] $end
$var wire 1 % HEX4 [5] $end
$var wire 1 & HEX4 [4] $end
$var wire 1 ' HEX4 [3] $end
$var wire 1 ( HEX4 [2] $end
$var wire 1 ) HEX4 [1] $end
$var wire 1 * HEX4 [0] $end
$var wire 1 + HEX3 [6] $end
$var wire 1 , HEX3 [5] $end
$var wire 1 - HEX3 [4] $end
$var wire 1 . HEX3 [3] $end
$var wire 1 / HEX3 [2] $end
$var wire 1 0 HEX3 [1] $end
$var wire 1 1 HEX3 [0] $end
$var wire 1 2 HEX2 [6] $end
$var wire 1 3 HEX2 [5] $end
$var wire 1 4 HEX2 [4] $end
$var wire 1 5 HEX2 [3] $end
$var wire 1 6 HEX2 [2] $end
$var wire 1 7 HEX2 [1] $end
$var wire 1 8 HEX2 [0] $end
$var wire 1 9 HEX1 [6] $end
$var wire 1 : HEX1 [5] $end
$var wire 1 ; HEX1 [4] $end
$var wire 1 < HEX1 [3] $end
$var wire 1 = HEX1 [2] $end
$var wire 1 > HEX1 [1] $end
$var wire 1 ? HEX1 [0] $end
$var wire 1 @ HEX0 [6] $end
$var wire 1 A HEX0 [5] $end
$var wire 1 B HEX0 [4] $end
$var wire 1 C HEX0 [3] $end
$var wire 1 D HEX0 [2] $end
$var wire 1 E HEX0 [1] $end
$var wire 1 F HEX0 [0] $end
$var wire 1 V sw_clean [9] $end
$var wire 1 W sw_clean [8] $end
$var wire 1 X sw_clean [7] $end
$var wire 1 Y sw_clean [6] $end
$var wire 1 Z sw_clean [5] $end
$var wire 1 [ sw_clean [4] $end
$var wire 1 \ sw_clean [3] $end
$var wire 1 ] sw_clean [2] $end
$var wire 1 ^ sw_clean [1] $end
$var wire 1 _ sw_clean [0] $end
$var wire 1 ` sw_rise [9] $end
$var wire 1 a sw_rise [8] $end
$var wire 1 b sw_rise [7] $end
$var wire 1 c sw_rise [6] $end
$var wire 1 d sw_rise [5] $end
$var wire 1 e sw_rise [4] $end
$var wire 1 f sw_rise [3] $end
$var wire 1 g sw_rise [2] $end
$var wire 1 h sw_rise [1] $end
$var wire 1 i sw_rise [0] $end
$var wire 1 j current_state [2] $end
$var wire 1 k current_state [1] $end
$var wire 1 l current_state [0] $end

$scope module debounce_inst $end
$var wire 1 T clk $end
$var wire 1 U rst_n $end
$var wire 1 J sw [9] $end
$var wire 1 K sw [8] $end
$var wire 1 L sw [7] $end
$var wire 1 M sw [6] $end
$var wire 1 N sw [5] $end
$var wire 1 O sw [4] $end
$var wire 1 P sw [3] $end
$var wire 1 Q sw [2] $end
$var wire 1 R sw [1] $end
$var wire 1 S sw [0] $end
$var reg 10 m sw_clean [9:0] $end
$var reg 20 n counter [19:0] $end
$upscope $end

$scope module edge_inst $end
$var wire 1 T clk $end
$var wire 1 U rst_n $end
$var wire 1 V sw_clean [9] $end
$var wire 1 W sw_clean [8] $end
$var wire 1 X sw_clean [7] $end
$var wire 1 Y sw_clean [6] $end
$var wire 1 Z sw_clean [5] $end
$var wire 1 [ sw_clean [4] $end
$var wire 1 \ sw_clean [3] $end
$var wire 1 ] sw_clean [2] $end
$var wire 1 ^ sw_clean [1] $end
$var wire 1 _ sw_clean [0] $end
$var reg 10 o sw_rise [9:0] $end
$var reg 10 p sw_prev [9:0] $end
$upscope $end

$scope module fsm_inst $end
$var parameter 3 q IDLE $end
$var parameter 3 r SW2 $end
$var parameter 3 s SW0 $end
$var parameter 3 t SW1 $end
$var parameter 3 u SW6 $end
$var parameter 3 v ERROR $end
$var parameter 3 w COMPLETE $end
$var wire 1 T clk $end
$var wire 1 U rst_n $end
$var wire 1 ` sw_rise [9] $end
$var wire 1 a sw_rise [8] $end
$var wire 1 b sw_rise [7] $end
$var wire 1 c sw_rise [6] $end
$var wire 1 d sw_rise [5] $end
$var wire 1 e sw_rise [4] $end
$var wire 1 f sw_rise [3] $end
$var wire 1 g sw_rise [2] $end
$var wire 1 h sw_rise [1] $end
$var wire 1 i sw_rise [0] $end
$var reg 3 x state [2:0] $end
$upscope $end

$scope module display_inst $end
$var wire 1 j state [2] $end
$var wire 1 k state [1] $end
$var wire 1 l state [0] $end
$var reg 7 y HEX4 [6:0] $end
$var reg 7 z HEX3 [6:0] $end
$var reg 7 { HEX2 [6:0] $end
$var reg 7 | HEX1 [6:0] $end
$var reg 7 } HEX0 [6:0] $end
$upscope $end
$upscope $end
$upscope $end
$enddefinitions $end
#0
$dumpvars
0!
0"
b0 #
b0 m
b0 n
b0 o
b0 p
b0 x
b1111111 y
b1111111 z
b1111111 {
b1111111 |
b1111111 }
b0 q
b1 r
b10 s
b11 t
b100 u
b101 v
b110 w
1*
1)
1(
1'
1&
1%
1$
11
10
1/
1.
1-
1,
1+
18
17
16
15
14
13
12
1?
1>
1=
1<
1;
1:
19
1F
1E
1D
1C
1B
1A
1@
0_
0^
0]
0\
0[
0Z
0Y
0X
0W
0V
0i
0h
0g
0f
0e
0d
0c
0b
0a
0`
0l
0k
0j
0I
0H
0G
0U
0T
0S
0R
0Q
0P
0O
0N
0M
0L
0K
0J
$end
#5000
1!
1T
#10000
0!
0T
#15000
1!
1T
1"
1U
#20000
0!
0T
#25000
1!
1T
b100 #
1Q
b1 n
#30000
0!
0T
#35000
1!
1T
b0 #
0Q
b10 n
#40000
0!
0T
#45000
1!
1T
b1 #
1S
b11 n
#50000
0!
0T
#55000
1!
1T
b0 #
0S
b100 n
#60000
0!
0T
#65000
1!
1T
b10 #
1R
b101 n
#70000
0!
0T
#75000
1!
1T
b0 #
0R
b110 n
#80000
0!
0T
#85000
1!
1T
b1000000 #
1M
b111 n
#90000
0!
0T
#95000
1!
1T
b0 #
0M
b1000 n
#100000
0!
0T
#105000
1!
1T
b1001 n
#110000
0!
0T
#115000
1!
1T
b1010 n
#120000
0!
0T
#125000
1!
1T
b1011 n
